rms_fastapi_service/__init__.py
rms_fastapi_service/exceptions.py
rms_fastapi_service/factory.py
rms_fastapi_service/sentry_setup.py
rms_fastapi_service/server.py
rms_fastapi_service/utils.py
rms_fastapi_service/clients/__init__.py
rms_fastapi_service/clients/base.py
rms_fastapi_service/clients/factory.py
rms_fastapi_service/clients/fast_api_client.py
rms_fastapi_service/clients/httpx.py
rms_fastapi_service/clients/schema/__init__.py
rms_fastapi_service/clients/schema/basic_types.py
rms_fastapi_service/clients/schema/config.py
rms_fastapi_service/clients/schema/constants.py
rms_fastapi_service/clients/schema/exceptions.py
rms_fastapi_service/clients/serializers/__init__.py
rms_fastapi_service/clients/serializers/base.py
rms_fastapi_service/clients/serializers/httpx_orjson_serializer.py
rms_fastapi_service/clients/serializers/httpx_raw_serializer.py
rms_fastapi_service/clients/transport/__init__.py
rms_fastapi_service/clients/transport/base_transport.py
rms_fastapi_service/clients/transport/httpx_trasport.py
rms_fastapi_service/healthchecks/__init__.py
rms_fastapi_service/healthchecks/base_healthcheck.py
rms_fastapi_service/healthchecks/databases.py
rms_fastapi_service/healthchecks/dummy.py
rms_fastapi_service/healthchecks/factory.py
rms_fastapi_service/healthchecks/httpx.py
rms_fastapi_service/logs/__init__.py
rms_fastapi_service/logs/handlers.py
rms_fastapi_service/logs/injectors.py
rms_fastapi_service/logs/log_config.py
rms_fastapi_service/metrics/__init__.py
rms_fastapi_service/metrics/default_metrics.py
rms_fastapi_service/metrics/metrics_collector.py
rms_fastapi_service/middlewares/__init__.py
rms_fastapi_service/middlewares/correlation.py
rms_fastapi_service/registry/__init__.py
rms_fastapi_service/registry/exception_handlers.py
rms_fastapi_service/registry/log_config.py
rms_fastapi_service/registry/middlewares.py
rms_fastapi_service/schemas/__init__.py
rms_fastapi_service/schemas/exception_handlers.py
rms_fastapi_service/schemas/middlewares.py
rms_fastapi_service-1.0.0.dist-info/METADATA
rms_fastapi_service-1.0.0.dist-info/WHEEL
rms_fastapi_service-1.0.0.dist-info/top_level.txt
rms_fastapi_service-1.0.0.dist-info/RECORD
