Metadata-Version: 2.1
Name: rms-fastapi-service
Version: 1.0.0
Summary: fastapi library
Home-page: https://gitlab.com/requirements-managment-systems/rms_fastapi_service
Author: Prokofev D.D.
Requires-Python: >=3.11
Requires-Dist: fastapi<1.0.0,>=0.100.0
Requires-Dist: httpx<1.0.0,>=0.22.0
Requires-Dist: orjson<4.0.0,>=3.6.7
Requires-Dist: prometheus-fastapi-instrumentator<8.0.0,>=5.0.0
Requires-Dist: pyhocon<1.0.0,>=0.3.59
Requires-Dist: sentry-sdk<3.0.0,>=1.11.1
Requires-Dist: setuptools<81.0.0,>=65.5.0
Requires-Dist: urllib3<3.0.0
Requires-Dist: uvicorn<1.0.0,>=0.16.0
Requires-Dist: uvloop<1.0.0,>=0.18.0
Requires-Dist: typing-extensions>=4.7.0
Requires-Dist: pyyaml>=5.0.0
Provides-Extra: databases
Requires-Dist: databases>=0.9.0; extra == "databases"
Provides-Extra: dev
Requires-Dist: mypy<2,>=1; extra == "dev"
Requires-Dist: wemake-python-styleguide>=0.16.1; extra == "dev"
Requires-Dist: pytest==8.3.5; extra == "dev"
Requires-Dist: pytest-asyncio==0.26.0; extra == "dev"
Requires-Dist: pytest-cov==6.1.1; extra == "dev"
Requires-Dist: pytest-mock==3.14.0; extra == "dev"
Requires-Dist: pytest-httpx>=0.26.0; extra == "dev"
Requires-Dist: black<=30,>=23.12.1; extra == "dev"
